setup.py
matip/README.md
matip/__init__.py
matip/driver.py
matip.egg-info/PKG-INFO
matip.egg-info/SOURCES.txt
matip.egg-info/dependency_links.txt
matip.egg-info/not-zip-safe
matip.egg-info/requires.txt
matip.egg-info/top_level.txt
matip/build/jars/move_manifest.jar
matip/build/jars/sign.jar
matip/build/jars/unsign.jar
matip/build/jars/verify.jar
matip/build/platform-tools/AdbWinApi.dll
matip/build/platform-tools/AdbWinUsbApi.dll
matip/build/platform-tools/aapt.exe
matip/build/platform-tools/adb.exe
matip/build/platform-tools/zipalign.exe
matip/build/selendroid/AndroidManifest.xml
matip/build/selendroid/android.jar
matip/build/selendroid/selendroid.apk
matip/build/unlock_apk/unlock.apk
matip/lib/__init__.py
matip/lib/android/__init__.py
matip/lib/android/common/__init__.py
matip/lib/android/common/adb.py
matip/lib/android/common/adb_actions.py
matip/lib/android/common/alert.py
matip/lib/android/common/by.py
matip/lib/android/common/command.py
matip/lib/android/common/device.py
matip/lib/android/common/gl.py
matip/lib/android/common/keys.py
matip/lib/android/common/log.py
matip/lib/android/common/mobileelement.py
matip/lib/android/common/mobilewebelement.py
matip/lib/android/common/proxy.py
matip/lib/android/common/selendroid.py
matip/lib/android/common/switch_to.py
matip/lib/android/common/touch_actions.py
matip/lib/android/common/wait.py
matip/lib/android/server/__init__.py
matip/lib/android/server/android_common.py
matip/lib/android/server/config.py
matip/lib/android/server/helpers.py
matip/lib/android/server/matip_server.py
matip/lib/android/server/selendroid.py